media_helper
tests
