Metadata-Version: 1.1
Name: django-media-helper
Version: 0.3.2
Summary: An image resizing and management app for Django
Home-page: https://github.com/brmc/django-media-helper
Author: Brian McClure
Author-email: django@jetbrains.com
License: MIT License
Download-URL: https://github.com/brmc/django-media-helper.git
Keywords: django,imaging,ajax
Platform: UNKNOWN
Classifier: Environment :: Web Environment
Classifier: Framework :: Django
Classifier: Intended Audience :: Developers
Classifier: Programming Language :: Python
Classifier: Programming Language :: Python :: 2.7
Classifier: Programming Language :: Python :: 3.4
Classifier: Programming Language :: Python :: 3.5
Requires: python (>= 2.7)
Requires: django (>= 1.8)
Requires: Pillow (>= 2.1.0)
